{"chunk_definitions":[{"row":17,"row_count":1,"visible":true,"expansion_state":0,"options":{"engine":"r","label":"unnamed-chunk-639","dev":"png"},"document_id":"BA33B25B","chunk_id":"cwqy8adt6x4gc","chunk_label":"unnamed-chunk-1"},{"row":25,"row_count":1,"visible":true,"expansion_state":0,"options":{"engine":"r","label":"unnamed-chunk-640","dev":"png"},"document_id":"BA33B25B","chunk_id":"cxbgs3avd7z7f","chunk_label":"unnamed-chunk-2"},{"row":38,"row_count":1,"visible":true,"expansion_state":0,"options":{"engine":"r","label":"unnamed-chunk-642","dev":"png"},"document_id":"BA33B25B","chunk_id":"cgmvj2s8r3xpd","chunk_label":"unnamed-chunk-4"},{"row":42,"row_count":1,"visible":true,"expansion_state":0,"options":{"engine":"r","label":"unnamed-chunk-643","dev":"png"},"document_id":"BA33B25B","chunk_id":"cg6e6tyt5jcyt","chunk_label":"unnamed-chunk-5"},{"row":46,"row_count":1,"visible":true,"expansion_state":0,"options":{"engine":"r","label":"unnamed-chunk-644","dev":"png"},"document_id":"BA33B25B","chunk_id":"ckq1xyd3rap7z","chunk_label":"unnamed-chunk-6"},{"row":50,"row_count":1,"visible":true,"expansion_state":0,"options":{"engine":"r","label":"unnamed-chunk-645","dev":"png"},"document_id":"BA33B25B","chunk_id":"c1u91wxhaaqau","chunk_label":"unnamed-chunk-7"},{"row":54,"row_count":1,"visible":true,"expansion_state":0,"options":{"engine":"r","label":"unnamed-chunk-646","dev":"png"},"document_id":"BA33B25B","chunk_id":"cqolkinlf6wvd","chunk_label":"unnamed-chunk-8"},{"row":58,"row_count":1,"visible":true,"expansion_state":0,"options":{"engine":"r","label":"unnamed-chunk-647","dev":"png"},"document_id":"BA33B25B","chunk_id":"c8y9r6mwawev4","chunk_label":"unnamed-chunk-9"},{"row":62,"row_count":1,"visible":true,"expansion_state":0,"options":{"engine":"r","label":"unnamed-chunk-648","dev":"png"},"document_id":"BA33B25B","chunk_id":"cizy1cgej9tnn","chunk_label":"unnamed-chunk-10"},{"row":66,"row_count":1,"visible":true,"expansion_state":0,"options":{"engine":"r","label":"unnamed-chunk-649","dev":"png"},"document_id":"BA33B25B","chunk_id":"cfu8lzli78j1r","chunk_label":"unnamed-chunk-11"},{"row":70,"row_count":1,"visible":true,"expansion_state":0,"options":{"engine":"r","label":"unnamed-chunk-650","dev":"png"},"document_id":"BA33B25B","chunk_id":"cjwsx5oszziy4","chunk_label":"unnamed-chunk-12"},{"row":91,"row_count":1,"visible":true,"expansion_state":0,"options":{"engine":"r","label":"unnamed-chunk-651","dev":"png"},"document_id":"BA33B25B","chunk_id":"cfn65gy0ltk3m","chunk_label":"unnamed-chunk-13"},{"row":109,"row_count":1,"visible":true,"expansion_state":0,"options":{"engine":"r","label":"unnamed-chunk-652","dev":"png"},"document_id":"BA33B25B","chunk_id":"c1q1gib8eow4k","chunk_label":"unnamed-chunk-14"},{"row":127,"row_count":1,"visible":true,"expansion_state":0,"options":{"engine":"r","label":"unnamed-chunk-653","dev":"png"},"document_id":"BA33B25B","chunk_id":"cdav43os9wd8l","chunk_label":"unnamed-chunk-15"},{"row":145,"row_count":1,"visible":true,"expansion_state":0,"options":{"engine":"r","label":"unnamed-chunk-654","dev":"png"},"document_id":"BA33B25B","chunk_id":"cedg6wy21g8t4","chunk_label":"unnamed-chunk-16"},{"row":163,"row_count":1,"visible":true,"expansion_state":0,"options":{"engine":"r","label":"unnamed-chunk-655","dev":"png"},"document_id":"BA33B25B","chunk_id":"cg4idolfmgg91","chunk_label":"unnamed-chunk-17"},{"row":181,"row_count":1,"visible":true,"expansion_state":0,"options":{"engine":"r","label":"unnamed-chunk-656","dev":"png"},"document_id":"BA33B25B","chunk_id":"cvd1ku4k1lv0n","chunk_label":"unnamed-chunk-18"},{"row":198,"row_count":1,"visible":true,"expansion_state":0,"options":{"engine":"r","label":"unnamed-chunk-657","dev":"png"},"document_id":"BA33B25B","chunk_id":"c3opkzn5p42al","chunk_label":"unnamed-chunk-19"},{"row":215,"row_count":1,"visible":true,"expansion_state":0,"options":{"engine":"r","label":"unnamed-chunk-658","dev":"png"},"document_id":"BA33B25B","chunk_id":"c4d0x05w1458l","chunk_label":"unnamed-chunk-20"},{"row":234,"row_count":1,"visible":true,"expansion_state":0,"options":{"engine":"r","label":"unnamed-chunk-659","dev":"png"},"document_id":"BA33B25B","chunk_id":"c4a927655g6ga","chunk_label":"unnamed-chunk-21"},{"row":251,"row_count":1,"visible":true,"expansion_state":0,"options":{"engine":"r","label":"unnamed-chunk-660","dev":"png"},"document_id":"BA33B25B","chunk_id":"cnd7it877ouz8","chunk_label":"unnamed-chunk-22"},{"row":268,"row_count":1,"visible":true,"expansion_state":0,"options":{"engine":"r","label":"unnamed-chunk-661","dev":"png"},"document_id":"BA33B25B","chunk_id":"c5h6rg4kvrxc9","chunk_label":"unnamed-chunk-23"},{"row":285,"row_count":1,"visible":true,"expansion_state":0,"options":{"engine":"r","label":"unnamed-chunk-662","dev":"png"},"document_id":"BA33B25B","chunk_id":"c1oc6yaa25h62","chunk_label":"unnamed-chunk-24"},{"row":302,"row_count":1,"visible":true,"expansion_state":0,"options":{"engine":"r","label":"unnamed-chunk-663","dev":"png"},"document_id":"BA33B25B","chunk_id":"cvdu8fqp56l3w","chunk_label":"unnamed-chunk-25"},{"row":319,"row_count":1,"visible":true,"expansion_state":0,"options":{"engine":"r","label":"unnamed-chunk-664","dev":"png"},"document_id":"BA33B25B","chunk_id":"c2pmftqn9tl5j","chunk_label":"unnamed-chunk-26"},{"row":336,"row_count":1,"visible":true,"expansion_state":0,"options":{"engine":"r","label":"unnamed-chunk-665","dev":"png"},"document_id":"BA33B25B","chunk_id":"cgi0ruwwpq3n4","chunk_label":"unnamed-chunk-27"},{"row":353,"row_count":1,"visible":true,"expansion_state":0,"options":{"engine":"r","label":"unnamed-chunk-666","dev":"png"},"document_id":"BA33B25B","chunk_id":"c5qxzqukn0eds","chunk_label":"unnamed-chunk-28"},{"row":370,"row_count":1,"visible":true,"expansion_state":0,"options":{"engine":"r","label":"unnamed-chunk-667","dev":"png"},"document_id":"BA33B25B","chunk_id":"cq04wyubf80lq","chunk_label":"unnamed-chunk-29"},{"row":391,"row_count":1,"visible":true,"expansion_state":0,"options":{"engine":"r","label":"unnamed-chunk-668","dev":"png"},"document_id":"BA33B25B","chunk_id":"cr22rampz5g4k","chunk_label":"unnamed-chunk-30"},{"row":408,"row_count":1,"visible":true,"expansion_state":0,"options":{"engine":"r","label":"unnamed-chunk-669","dev":"png"},"document_id":"BA33B25B","chunk_id":"cpowop7vxl7b3","chunk_label":"unnamed-chunk-31"},{"row":425,"row_count":1,"visible":true,"expansion_state":0,"options":{"engine":"r","label":"unnamed-chunk-670","dev":"png"},"document_id":"BA33B25B","chunk_id":"c21wle7ul0vut","chunk_label":"unnamed-chunk-32"},{"row":442,"row_count":1,"visible":true,"expansion_state":0,"options":{"engine":"r","label":"unnamed-chunk-671","dev":"png"},"document_id":"BA33B25B","chunk_id":"c2mx2mnbd5qdh","chunk_label":"unnamed-chunk-33"},{"row":459,"row_count":1,"visible":true,"expansion_state":0,"options":{"engine":"r","label":"unnamed-chunk-672","dev":"png"},"document_id":"BA33B25B","chunk_id":"c72borhocybgh","chunk_label":"unnamed-chunk-34"},{"row":476,"row_count":1,"visible":true,"expansion_state":0,"options":{"engine":"r","label":"unnamed-chunk-673","dev":"png"},"document_id":"BA33B25B","chunk_id":"ccvo8zjnp749b","chunk_label":"unnamed-chunk-35"},{"row":493,"row_count":1,"visible":true,"expansion_state":0,"options":{"engine":"r","label":"unnamed-chunk-674","dev":"png"},"document_id":"BA33B25B","chunk_id":"c36p8zd71oyss","chunk_label":"unnamed-chunk-36"},{"row":510,"row_count":1,"visible":true,"expansion_state":0,"options":{"engine":"r","label":"unnamed-chunk-675","dev":"png"},"document_id":"BA33B25B","chunk_id":"c80tjstmgk0vn","chunk_label":"unnamed-chunk-37"},{"row":527,"row_count":1,"visible":true,"expansion_state":0,"options":{"engine":"r","label":"unnamed-chunk-676","dev":"png"},"document_id":"BA33B25B","chunk_id":"cnpj8ldh52wac","chunk_label":"unnamed-chunk-38"},{"row":546,"row_count":1,"visible":true,"expansion_state":0,"options":{"engine":"r","label":"unnamed-chunk-677","dev":"png"},"document_id":"BA33B25B","chunk_id":"c958o8yitotf3","chunk_label":"unnamed-chunk-39"},{"row":565,"row_count":1,"visible":true,"expansion_state":0,"options":{"engine":"r","label":"unnamed-chunk-678","dev":"png"},"document_id":"BA33B25B","chunk_id":"cf133vdu1dv6n","chunk_label":"unnamed-chunk-40"},{"row":582,"row_count":1,"visible":true,"expansion_state":0,"options":{"engine":"r","label":"unnamed-chunk-679","dev":"png"},"document_id":"BA33B25B","chunk_id":"car24os3mwvfa","chunk_label":"unnamed-chunk-41"},{"row":599,"row_count":1,"visible":true,"expansion_state":0,"options":{"engine":"r","label":"unnamed-chunk-680","dev":"png"},"document_id":"BA33B25B","chunk_id":"ctd2umakaf163","chunk_label":"unnamed-chunk-42"},{"row":616,"row_count":1,"visible":true,"expansion_state":0,"options":{"engine":"r","label":"unnamed-chunk-681","dev":"png"},"document_id":"BA33B25B","chunk_id":"c2uai14xxl7wp","chunk_label":"unnamed-chunk-43"},{"row":633,"row_count":1,"visible":true,"expansion_state":0,"options":{"engine":"r","label":"unnamed-chunk-682","dev":"png"},"document_id":"BA33B25B","chunk_id":"cny2tjtvbhmxg","chunk_label":"unnamed-chunk-44"},{"row":650,"row_count":1,"visible":true,"expansion_state":0,"options":{"engine":"r","label":"unnamed-chunk-683","dev":"png"},"document_id":"BA33B25B","chunk_id":"c4qcgcpi2qf9q","chunk_label":"unnamed-chunk-45"},{"row":667,"row_count":1,"visible":true,"expansion_state":0,"options":{"engine":"r","label":"unnamed-chunk-684","dev":"png"},"document_id":"BA33B25B","chunk_id":"cgebdeqal3xz6","chunk_label":"unnamed-chunk-46"},{"row":685,"row_count":1,"visible":true,"expansion_state":0,"options":{"engine":"r","label":"unnamed-chunk-685","dev":"png"},"document_id":"BA33B25B","chunk_id":"ctf2ot9kd9zqr","chunk_label":"unnamed-chunk-47"},{"row":702,"row_count":1,"visible":true,"expansion_state":0,"options":{"engine":"r","label":"unnamed-chunk-686","dev":"png"},"document_id":"BA33B25B","chunk_id":"c1n9i93jkczdi","chunk_label":"unnamed-chunk-48"},{"row":719,"row_count":1,"visible":true,"expansion_state":0,"options":{"engine":"r","label":"unnamed-chunk-687","dev":"png"},"document_id":"BA33B25B","chunk_id":"c4eb5egsu8mow","chunk_label":"unnamed-chunk-49"},{"row":736,"row_count":1,"visible":true,"expansion_state":0,"options":{"engine":"r","label":"unnamed-chunk-688","dev":"png"},"document_id":"BA33B25B","chunk_id":"cndyqux64bl0l","chunk_label":"unnamed-chunk-50"},{"row":753,"row_count":1,"visible":true,"expansion_state":0,"options":{"engine":"r","label":"unnamed-chunk-689","dev":"png"},"document_id":"BA33B25B","chunk_id":"ceb5nahk022hw","chunk_label":"unnamed-chunk-51"},{"row":770,"row_count":1,"visible":true,"expansion_state":0,"options":{"engine":"r","label":"unnamed-chunk-690","dev":"png"},"document_id":"BA33B25B","chunk_id":"cc0p9pyxwcshx","chunk_label":"unnamed-chunk-52"},{"row":787,"row_count":1,"visible":true,"expansion_state":0,"options":{"engine":"r","label":"unnamed-chunk-691","dev":"png"},"document_id":"BA33B25B","chunk_id":"c1848i0z65hla","chunk_label":"unnamed-chunk-53"},{"row":804,"row_count":1,"visible":true,"expansion_state":0,"options":{"engine":"r","label":"unnamed-chunk-692","dev":"png"},"document_id":"BA33B25B","chunk_id":"cmr5uodj0frqd","chunk_label":"unnamed-chunk-54"},{"row":823,"row_count":1,"visible":true,"expansion_state":0,"options":{"engine":"r","label":"unnamed-chunk-693","dev":"png"},"document_id":"BA33B25B","chunk_id":"cbhbly5y3b8yg","chunk_label":"unnamed-chunk-55"},{"row":840,"row_count":1,"visible":true,"expansion_state":0,"options":{"engine":"r","label":"unnamed-chunk-694","dev":"png"},"document_id":"BA33B25B","chunk_id":"cvujs1begmtfm","chunk_label":"unnamed-chunk-56"},{"row":857,"row_count":1,"visible":true,"expansion_state":0,"options":{"engine":"r","label":"unnamed-chunk-695","dev":"png"},"document_id":"BA33B25B","chunk_id":"c7u1b7s9rx52s","chunk_label":"unnamed-chunk-57"},{"row":874,"row_count":1,"visible":true,"expansion_state":0,"options":{"engine":"r","label":"unnamed-chunk-696","dev":"png"},"document_id":"BA33B25B","chunk_id":"cgdrsdxfbd7oa","chunk_label":"unnamed-chunk-58"},{"row":891,"row_count":1,"visible":true,"expansion_state":0,"options":{"engine":"r","label":"unnamed-chunk-697","dev":"png"},"document_id":"BA33B25B","chunk_id":"cmafy1qyn9ygv","chunk_label":"unnamed-chunk-59"},{"row":908,"row_count":1,"visible":true,"expansion_state":0,"options":{"engine":"r","label":"unnamed-chunk-698","dev":"png"},"document_id":"BA33B25B","chunk_id":"clswrhhanc23k","chunk_label":"unnamed-chunk-60"},{"row":925,"row_count":1,"visible":true,"expansion_state":0,"options":{"engine":"r","label":"unnamed-chunk-699","dev":"png"},"document_id":"BA33B25B","chunk_id":"cx3i7b7bvui6m","chunk_label":"unnamed-chunk-61"},{"row":942,"row_count":1,"visible":true,"expansion_state":0,"options":{"engine":"r","label":"unnamed-chunk-700","dev":"png"},"document_id":"BA33B25B","chunk_id":"cmq8okt416lw6","chunk_label":"unnamed-chunk-62"},{"row":959,"row_count":1,"visible":true,"expansion_state":0,"options":{"engine":"r","label":"unnamed-chunk-701","dev":"png"},"document_id":"BA33B25B","chunk_id":"ck7y1hkiohoe5","chunk_label":"unnamed-chunk-63"},{"row":976,"row_count":1,"visible":true,"expansion_state":0,"options":{"engine":"r","label":"unnamed-chunk-702","dev":"png"},"document_id":"BA33B25B","chunk_id":"c0jqg6py0b6q5","chunk_label":"unnamed-chunk-64"},{"row":993,"row_count":1,"visible":true,"expansion_state":0,"options":{"engine":"r","label":"unnamed-chunk-703","dev":"png"},"document_id":"BA33B25B","chunk_id":"c6vwse2jdthrl","chunk_label":"unnamed-chunk-65"},{"row":1010,"row_count":1,"visible":true,"expansion_state":0,"options":{"engine":"r","label":"unnamed-chunk-704","dev":"png"},"document_id":"BA33B25B","chunk_id":"cb0wq7ipish91","chunk_label":"unnamed-chunk-66"},{"row":1027,"row_count":1,"visible":true,"expansion_state":0,"options":{"engine":"r","label":"unnamed-chunk-705","dev":"png"},"document_id":"BA33B25B","chunk_id":"c3e8vu4f4k04s","chunk_label":"unnamed-chunk-67"},{"row":1044,"row_count":1,"visible":true,"expansion_state":0,"options":{"engine":"r","label":"unnamed-chunk-706","dev":"png"},"document_id":"BA33B25B","chunk_id":"cmujg1sw0zmev","chunk_label":"unnamed-chunk-68"},{"row":1061,"row_count":1,"visible":true,"expansion_state":0,"options":{"engine":"r","label":"unnamed-chunk-707","dev":"png"},"document_id":"BA33B25B","chunk_id":"c7b3dbje9sgyp","chunk_label":"unnamed-chunk-69"},{"row":1080,"row_count":1,"visible":true,"expansion_state":0,"options":{"engine":"r","label":"unnamed-chunk-708","dev":"png"},"document_id":"BA33B25B","chunk_id":"cx5nr891jmhj3","chunk_label":"unnamed-chunk-70"},{"row":1097,"row_count":1,"visible":true,"expansion_state":0,"options":{"engine":"r","label":"unnamed-chunk-709","dev":"png"},"document_id":"BA33B25B","chunk_id":"c19qs0ps73ypg","chunk_label":"unnamed-chunk-71"},{"row":1114,"row_count":1,"visible":true,"expansion_state":0,"options":{"engine":"r","label":"unnamed-chunk-710","dev":"png"},"document_id":"BA33B25B","chunk_id":"cg6gttwavtx15","chunk_label":"unnamed-chunk-72"},{"row":1133,"row_count":1,"visible":true,"expansion_state":0,"options":{"engine":"r","label":"unnamed-chunk-711","dev":"png"},"document_id":"BA33B25B","chunk_id":"clcfpj4ctjyv1","chunk_label":"unnamed-chunk-73"},{"row":1150,"row_count":1,"visible":true,"expansion_state":0,"options":{"engine":"r","label":"unnamed-chunk-712","dev":"png"},"document_id":"BA33B25B","chunk_id":"cttb14c6jw5lv","chunk_label":"unnamed-chunk-74"},{"row":1167,"row_count":1,"visible":true,"expansion_state":0,"options":{"engine":"r","label":"unnamed-chunk-713","dev":"png"},"document_id":"BA33B25B","chunk_id":"c0j3orpqi4mhu","chunk_label":"unnamed-chunk-75"},{"row":1184,"row_count":1,"visible":true,"expansion_state":0,"options":{"engine":"r","label":"unnamed-chunk-714","dev":"png"},"document_id":"BA33B25B","chunk_id":"cvjt8c2b0jqha","chunk_label":"unnamed-chunk-76"},{"row":1201,"row_count":1,"visible":true,"expansion_state":0,"options":{"engine":"r","label":"unnamed-chunk-715","dev":"png"},"document_id":"BA33B25B","chunk_id":"cpa3xxzw3zoxl","chunk_label":"unnamed-chunk-77"},{"row":1218,"row_count":1,"visible":true,"expansion_state":0,"options":{"engine":"r","label":"unnamed-chunk-716","dev":"png"},"document_id":"BA33B25B","chunk_id":"ce9p6suiar47u","chunk_label":"unnamed-chunk-78"},{"row":1235,"row_count":1,"visible":true,"expansion_state":0,"options":{"engine":"r","label":"unnamed-chunk-717","dev":"png"},"document_id":"BA33B25B","chunk_id":"cllmopb23y6ve","chunk_label":"unnamed-chunk-79"},{"row":1254,"row_count":1,"visible":true,"expansion_state":0,"options":{"engine":"r","label":"unnamed-chunk-718","dev":"png"},"document_id":"BA33B25B","chunk_id":"cguhimredqlan","chunk_label":"unnamed-chunk-80"},{"row":1273,"row_count":1,"visible":true,"expansion_state":0,"options":{"engine":"r","label":"unnamed-chunk-719","dev":"png"},"document_id":"BA33B25B","chunk_id":"ctqhzpxq2fj3m","chunk_label":"unnamed-chunk-81"},{"row":1290,"row_count":1,"visible":true,"expansion_state":0,"options":{"engine":"r","label":"unnamed-chunk-720","dev":"png"},"document_id":"BA33B25B","chunk_id":"c0vr45lxdxf3i","chunk_label":"unnamed-chunk-82"},{"row":1307,"row_count":1,"visible":true,"expansion_state":0,"options":{"engine":"r","label":"unnamed-chunk-721","dev":"png"},"document_id":"BA33B25B","chunk_id":"c7d21nslwuyeo","chunk_label":"unnamed-chunk-83"},{"row":1324,"row_count":1,"visible":true,"expansion_state":0,"options":{"engine":"r","label":"unnamed-chunk-722","dev":"png"},"document_id":"BA33B25B","chunk_id":"ccwk82ulxp0vh","chunk_label":"unnamed-chunk-84"},{"row":1341,"row_count":1,"visible":true,"expansion_state":0,"options":{"engine":"r","label":"unnamed-chunk-723","dev":"png"},"document_id":"BA33B25B","chunk_id":"cugamlo7594f5","chunk_label":"unnamed-chunk-85"},{"row":1358,"row_count":1,"visible":true,"expansion_state":0,"options":{"engine":"r","label":"unnamed-chunk-724","dev":"png"},"document_id":"BA33B25B","chunk_id":"c0ugcs7th36on","chunk_label":"unnamed-chunk-86"},{"row":1375,"row_count":1,"visible":true,"expansion_state":0,"options":{"engine":"r","label":"unnamed-chunk-725","dev":"png"},"document_id":"BA33B25B","chunk_id":"c9toe61egujeo","chunk_label":"unnamed-chunk-87"},{"row":1392,"row_count":1,"visible":true,"expansion_state":0,"options":{"engine":"r","label":"unnamed-chunk-726","dev":"png"},"document_id":"BA33B25B","chunk_id":"cj3z1495i1cii","chunk_label":"unnamed-chunk-88"},{"row":1409,"row_count":1,"visible":true,"expansion_state":0,"options":{"engine":"r","label":"unnamed-chunk-727","dev":"png"},"document_id":"BA33B25B","chunk_id":"cwnnsb9df3px9","chunk_label":"unnamed-chunk-89"},{"row":1426,"row_count":1,"visible":true,"expansion_state":0,"options":{"engine":"r","label":"unnamed-chunk-728","dev":"png"},"document_id":"BA33B25B","chunk_id":"cnhkfaxk1g81g","chunk_label":"unnamed-chunk-90"},{"row":1443,"row_count":1,"visible":true,"expansion_state":0,"options":{"engine":"r","label":"unnamed-chunk-729","dev":"png"},"document_id":"BA33B25B","chunk_id":"cfzetp9xg2rd7","chunk_label":"unnamed-chunk-91"},{"row":1460,"row_count":1,"visible":true,"expansion_state":0,"options":{"engine":"r","label":"unnamed-chunk-730","dev":"png"},"document_id":"BA33B25B","chunk_id":"c9mhfjidd54j5","chunk_label":"unnamed-chunk-92"},{"row":1477,"row_count":1,"visible":true,"expansion_state":0,"options":{"engine":"r","label":"unnamed-chunk-731","dev":"png"},"document_id":"BA33B25B","chunk_id":"cfq19g6bztrys","chunk_label":"unnamed-chunk-93"},{"row":1496,"row_count":1,"visible":true,"expansion_state":0,"options":{"engine":"r","label":"unnamed-chunk-732","dev":"png"},"document_id":"BA33B25B","chunk_id":"c6v780cpil608","chunk_label":"unnamed-chunk-94"},{"row":1513,"row_count":1,"visible":true,"expansion_state":0,"options":{"engine":"r","label":"unnamed-chunk-733","dev":"png"},"document_id":"BA33B25B","chunk_id":"cf6r0bsh5beyz","chunk_label":"unnamed-chunk-95"},{"row":1530,"row_count":1,"visible":true,"expansion_state":0,"options":{"engine":"r","label":"unnamed-chunk-734","dev":"png"},"document_id":"BA33B25B","chunk_id":"c8emhcpz5yi5n","chunk_label":"unnamed-chunk-96"},{"row":1547,"row_count":1,"visible":true,"expansion_state":0,"options":{"engine":"r","label":"unnamed-chunk-735","dev":"png"},"document_id":"BA33B25B","chunk_id":"co7fu4jo3qfzg","chunk_label":"unnamed-chunk-97"},{"row":1564,"row_count":1,"visible":true,"expansion_state":0,"options":{"engine":"r","label":"unnamed-chunk-736","dev":"png"},"document_id":"BA33B25B","chunk_id":"cf2zec6qf3kij","chunk_label":"unnamed-chunk-98"},{"row":1582,"row_count":1,"visible":true,"expansion_state":0,"options":{"engine":"r","label":"unnamed-chunk-737","dev":"png"},"document_id":"BA33B25B","chunk_id":"ca6zlalrj5y8i","chunk_label":"unnamed-chunk-99"},{"row":1604,"row_count":1,"visible":true,"expansion_state":0,"options":{"engine":"r","label":"unnamed-chunk-738","dev":"png"},"document_id":"BA33B25B","chunk_id":"ca8rytgkr1zgx","chunk_label":"unnamed-chunk-100"},{"row":1621,"row_count":1,"visible":true,"expansion_state":0,"options":{"engine":"r","label":"unnamed-chunk-739","dev":"png"},"document_id":"BA33B25B","chunk_id":"cfecbomz61got","chunk_label":"unnamed-chunk-101"},{"row":1638,"row_count":1,"visible":true,"expansion_state":0,"options":{"engine":"r","label":"unnamed-chunk-740","dev":"png"},"document_id":"BA33B25B","chunk_id":"cc19z5gz35ooo","chunk_label":"unnamed-chunk-102"},{"row":1655,"row_count":1,"visible":true,"expansion_state":0,"options":{"engine":"r","label":"unnamed-chunk-741","dev":"png"},"document_id":"BA33B25B","chunk_id":"cw0gk75eyuxu7","chunk_label":"unnamed-chunk-103"},{"row":1672,"row_count":1,"visible":true,"expansion_state":0,"options":{"engine":"r","label":"unnamed-chunk-742","dev":"png"},"document_id":"BA33B25B","chunk_id":"csjsu0zx000mg","chunk_label":"unnamed-chunk-104"},{"row":1689,"row_count":1,"visible":true,"expansion_state":0,"options":{"engine":"r","label":"unnamed-chunk-743","dev":"png"},"document_id":"BA33B25B","chunk_id":"cait55f14hlqa","chunk_label":"unnamed-chunk-105"},{"row":1708,"row_count":1,"visible":true,"expansion_state":0,"options":{"engine":"r","label":"unnamed-chunk-744","dev":"png"},"document_id":"BA33B25B","chunk_id":"con9gut7mxgan","chunk_label":"unnamed-chunk-106"},{"row":1725,"row_count":1,"visible":true,"expansion_state":0,"options":{"engine":"r","label":"unnamed-chunk-745","dev":"png"},"document_id":"BA33B25B","chunk_id":"ceu7xlsme4l1g","chunk_label":"unnamed-chunk-107"},{"row":1742,"row_count":1,"visible":true,"expansion_state":0,"options":{"engine":"r","label":"unnamed-chunk-746","dev":"png"},"document_id":"BA33B25B","chunk_id":"c9ayfa54ei8tf","chunk_label":"unnamed-chunk-108"},{"row":1759,"row_count":1,"visible":true,"expansion_state":0,"options":{"engine":"r","label":"unnamed-chunk-747","dev":"png"},"document_id":"BA33B25B","chunk_id":"chdr399br4w8u","chunk_label":"unnamed-chunk-109"},{"row":1776,"row_count":1,"visible":true,"expansion_state":0,"options":{"engine":"r","label":"unnamed-chunk-748","dev":"png"},"document_id":"BA33B25B","chunk_id":"ca3k19lng9p47","chunk_label":"unnamed-chunk-110"},{"row":1793,"row_count":1,"visible":true,"expansion_state":0,"options":{"engine":"r","label":"unnamed-chunk-749","dev":"png"},"document_id":"BA33B25B","chunk_id":"c5f6y57emh233","chunk_label":"unnamed-chunk-111"},{"row":1810,"row_count":1,"visible":true,"expansion_state":0,"options":{"engine":"r","label":"unnamed-chunk-750","dev":"png"},"document_id":"BA33B25B","chunk_id":"c300ysdv8h1ky","chunk_label":"unnamed-chunk-112"},{"row":32,"row_count":1,"visible":true,"expansion_state":0,"options":{"engine":"r","label":"unnamed-chunk-641","dev":"png"},"document_id":"BA33B25B","chunk_id":"cmwmipv3roqgf","chunk_label":"unnamed-chunk-3"},{"row":1834,"row_count":1,"visible":true,"expansion_state":0,"options":{"engine":"r","label":"unnamed-chunk-751","dev":"png"},"document_id":"BA33B25B","chunk_id":"cbhh1bimbnq61","chunk_label":"unnamed-chunk-113"},{"row":1851,"row_count":1,"visible":true,"expansion_state":0,"options":{"engine":"r","label":"unnamed-chunk-752","dev":"png"},"document_id":"BA33B25B","chunk_id":"cmd32dm5w0nog","chunk_label":"unnamed-chunk-114"},{"row":1858,"row_count":1,"visible":true,"expansion_state":0,"options":{"engine":"r","label":"unnamed-chunk-753","dev":"png"},"document_id":"BA33B25B","chunk_id":"cujh2mtbh2x87","chunk_label":"unnamed-chunk-115"},{"row":1872,"row_count":1,"visible":true,"expansion_state":0,"options":{"engine":"r","label":"unnamed-chunk-754","dev":"png"},"document_id":"BA33B25B","chunk_id":"c8zu0y7w79bot","chunk_label":"unnamed-chunk-116"},{"row":1893,"row_count":1,"visible":true,"expansion_state":0,"options":{"engine":"r","label":"unnamed-chunk-755","dev":"png"},"document_id":"BA33B25B","chunk_id":"c3bkis8lpos69","chunk_label":"unnamed-chunk-117"},{"row":1912,"row_count":1,"visible":true,"expansion_state":0,"options":{"engine":"r","label":"unnamed-chunk-756","dev":"png"},"document_id":"BA33B25B","chunk_id":"cvyqt10hysqox","chunk_label":"unnamed-chunk-118"},{"row":1931,"row_count":1,"visible":true,"expansion_state":0,"options":{"engine":"r","label":"unnamed-chunk-757","dev":"png"},"document_id":"BA33B25B","chunk_id":"cvdamep4rjl86","chunk_label":"unnamed-chunk-119"},{"row":1950,"row_count":1,"visible":true,"expansion_state":0,"options":{"engine":"r","label":"unnamed-chunk-758","dev":"png"},"document_id":"BA33B25B","chunk_id":"ck06b2h6ojnun","chunk_label":"unnamed-chunk-120"},{"row":1969,"row_count":1,"visible":true,"expansion_state":0,"options":{"engine":"r","label":"unnamed-chunk-759","dev":"png"},"document_id":"BA33B25B","chunk_id":"cxznoxemws4fy","chunk_label":"unnamed-chunk-121"},{"row":1988,"row_count":1,"visible":true,"expansion_state":0,"options":{"engine":"r","label":"unnamed-chunk-760","dev":"png"},"document_id":"BA33B25B","chunk_id":"c1pv8o50lrc7v","chunk_label":"unnamed-chunk-122"},{"row":2007,"row_count":1,"visible":true,"expansion_state":0,"options":{"engine":"r","label":"unnamed-chunk-761","dev":"png"},"document_id":"BA33B25B","chunk_id":"ctoyucachqcke","chunk_label":"unnamed-chunk-123"},{"row":2026,"row_count":1,"visible":true,"expansion_state":0,"options":{"engine":"r","label":"unnamed-chunk-762","dev":"png"},"document_id":"BA33B25B","chunk_id":"ck8fc2z7dsxs8","chunk_label":"unnamed-chunk-124"},{"row":2045,"row_count":1,"visible":true,"expansion_state":0,"options":{"engine":"r","label":"unnamed-chunk-763","dev":"png"},"document_id":"BA33B25B","chunk_id":"crswfc4m0mvkx","chunk_label":"unnamed-chunk-125"},{"row":2064,"row_count":1,"visible":true,"expansion_state":0,"options":{"engine":"r","label":"unnamed-chunk-764","dev":"png"},"document_id":"BA33B25B","chunk_id":"ca96qj1b1tfvu","chunk_label":"unnamed-chunk-126"},{"row":2083,"row_count":1,"visible":true,"expansion_state":0,"options":{"engine":"r","label":"unnamed-chunk-765","dev":"png"},"document_id":"BA33B25B","chunk_id":"c7y3ffx3fnhx8","chunk_label":"unnamed-chunk-127"},{"row":2102,"row_count":1,"visible":true,"expansion_state":0,"options":{"engine":"r","label":"unnamed-chunk-766","dev":"png"},"document_id":"BA33B25B","chunk_id":"c3yj696ppyw55","chunk_label":"unnamed-chunk-128"},{"row":2121,"row_count":1,"visible":true,"expansion_state":0,"options":{"engine":"r","label":"unnamed-chunk-767","dev":"png"},"document_id":"BA33B25B","chunk_id":"cufuvzvsb0c5m","chunk_label":"unnamed-chunk-129"},{"row":2140,"row_count":1,"visible":true,"expansion_state":0,"options":{"engine":"r","label":"unnamed-chunk-768","dev":"png"},"document_id":"BA33B25B","chunk_id":"cd7vnidihqz5x","chunk_label":"unnamed-chunk-130"}],"doc_write_time":1762540262}